django_jsonfield_backport/__init__.py
django_jsonfield_backport/apps.py
django_jsonfield_backport/features.py
django_jsonfield_backport/forms.py
django_jsonfield_backport/models.py
django_jsonfield_backport-1.0.5.dist-info/LICENSE
django_jsonfield_backport-1.0.5.dist-info/METADATA
django_jsonfield_backport-1.0.5.dist-info/WHEEL
django_jsonfield_backport-1.0.5.dist-info/top_level.txt
django_jsonfield_backport-1.0.5.dist-info/RECORD
