Metadata-Version: 2.1
Name: django-jsonfield-backport
Version: 1.0.5
Summary: Backport of the cross-DB JSONField model and form fields from Django 3.1.
Home-page: https://github.com/laymonage/django-jsonfield-backport
Author: sage
Author-email: laymonage@gmail.com
License: BSD
Keywords: django jsonfield json backport database models forms fields
Platform: any
Classifier: Development Status :: 5 - Production/Stable
Classifier: Framework :: Django
Classifier: Framework :: Django :: 2.2
Classifier: Framework :: Django :: 3.0
Classifier: Intended Audience :: Developers
Classifier: License :: OSI Approved :: BSD License
Classifier: Operating System :: OS Independent
Classifier: Programming Language :: Python :: 3
Classifier: Programming Language :: Python :: 3.5
Classifier: Programming Language :: Python :: 3.6
Classifier: Programming Language :: Python :: 3.7
Classifier: Programming Language :: Python :: 3.8
Classifier: Programming Language :: Python :: 3.9
Classifier: Programming Language :: Python :: 3 :: Only
Requires-Python: >=3.5
License-File: LICENSE
